LogExportTable2.py
setup.py
LogExportTable2.egg-info/PKG-INFO
LogExportTable2.egg-info/SOURCES.txt
LogExportTable2.egg-info/dependency_links.txt
LogExportTable2.egg-info/requires.txt
LogExportTable2.egg-info/top_level.txt