Metadata-Version: 2.1
Name: LogExportTable2
Version: 1.0.0
Summary: Log Export Table2
Author: SINTT
Author-email: bbhh66606@gmail.com
Requires-Dist: pyodbc
Requires-Dist: Pillow
